{
  "cla": {
    "task_type": "classification",
    "model_filename": "classification/mobilenet.pt",
    "classes": [
      "flying_birds",
      "large_quadcopters",
      "small_quadcopters",
      "winged_drones"
    ],
    "creation_date": "01-01-21 13:23"
  },
  "sen": {
    "task_type": "sentiment_analysis",
    "model_filename": "sentiment_analysis/sentiment_analysis.pt",
    "metadata_filename": "sentiment_analysis/sentiment_analysis_metadata.pkl",
    "creation_date": "01-01-21 13:23"
  }
}
